pygitguardian-1.28.0.dist-info/METADATA
pygitguardian-1.28.0.dist-info/WHEEL
pygitguardian-1.28.0.dist-info/entry_points.txt
pygitguardian-1.28.0.dist-info/licenses/LICENSE
pygitguardian/__init__.py
pygitguardian/client.py
pygitguardian/config.py
pygitguardian/models.py
pygitguardian/models_utils.py
pygitguardian/py.typed
pygitguardian-1.28.0.dist-info/RECORD
