Metadata-Version: 2.1
Name: pygitguardian
Version: 1.28.0
Summary: Python Wrapper for GitGuardian's API -- Scan security policy breaks everywhere
Keywords: api-client devsecops secrets-detection security-tools library gitguardian
Author-Email: GitGuardian <support@gitguardian.com>
Maintainer-Email: GitGuardian <support@gitguardian.com>
License: MIT
Classifier: Development Status :: 5 - Production/Stable
Classifier: Intended Audience :: Developers
Classifier: License :: OSI Approved :: MIT License
Classifier: Natural Language :: English
Classifier: Operating System :: OS Independent
Classifier: Programming Language :: Python
Classifier: Programming Language :: Python :: 3
Classifier: Programming Language :: Python :: 3.10
Classifier: Programming Language :: Python :: 3.11
Classifier: Programming Language :: Python :: 3.12
Classifier: Programming Language :: Python :: 3.8
Classifier: Programming Language :: Python :: 3.9
Classifier: Topic :: Security
Project-URL: Homepage, https://github.com/GitGuardian/py-gitguardian
Requires-Python: >=3.8
Requires-Dist: marshmallow<4,>=3.5
Requires-Dist: requests<3,>=2
Requires-Dist: marshmallow-dataclass<8.6.0,>=8.5.8
Requires-Dist: typing-extensions
Requires-Dist: setuptools>=70.1.0
